sparta_schema/__init__.py
sparta_schema/jet/fob.py
sparta_schema-0.1.0.dist-info/WHEEL
sparta_schema-0.1.0.dist-info/METADATA
sparta_schema-0.1.0.dist-info/RECORD
