Metadata-Version: 2.1
Name: sparta-schema
Version: 0.1.0
Summary: 
Author: alexander.rembridge
Author-email: alexander.rembridge@spartacommodities.com
Requires-Python: >=3.10,<4.0
Classifier: Programming Language :: Python :: 3
Classifier: Programming Language :: Python :: 3.10
Classifier: Programming Language :: Python :: 3.11
Requires-Dist: pydantic (>=1.10.6,<2.0.0)
